{"gameCounter":81,"topLevelStats":{"kills":[6,3,1,3,6,0,5,2,2,9,0,1,3,1,8,1,1,0,1,1,0,0,0,0,1,1,0],"deaths":[1,3,4,5,1,1,5,1,6,0,1,10,3,3,5,1,5,3,2,11,4,4,2,3,0,4,6],"assists":[14,8,10,8,12,2,22,12,6,12,15,18,15,11,13,2,3,12,14,23,16,21,18,22,14,17,2],"CS":[39,65,48,53,45,23,44,26,53,18,22,50,77,30,41,26,33,31,39,26,54,49,34,40,42,51,26],"gold":[12708,14065,13158,14074,13955,7450,12089,9863,10413,10193,8675,14558,14737,9567,11825,8938,7900,9173,9457,11355,10507,12329,9285,9141,8586,10954,5419],"position":["JUNGLE","JUNGLE","JUNGLE","JUNGLE","JUNGLE","JUNGLE","JUNGLE","JUNGLE","JUNGLE","JUNGLE","JUNGLE","JUNGLE","JUNGLE","JUNGLE","JUNGLE","JUNGLE","JUNGLE","DUO_SUPPORT","DUO_SUPPORT","DUO_SUPPORT","DUO_SUPPORT","DUO_SUPPORT","DUO_SUPPORT","DUO_SUPPORT","DUO_SUPPORT","DUO_SUPPORT","DUO_SUPPORT"]},"additionaldata":{"championId":[60,5,60,77,106,154,79,106,254,106,154,64,154,60,154,154,104,201,201,201,201,12,201,201,12,201,12]},"timlineStats":{"creepsPerMinDeltas":[{"zeroToTen":0.1,"tenToTwenty":0.8,"twentyToThirty":2.5},{"zeroToTen":0,"tenToTwenty":1.7,"twentyToThirty":1.8,"thirtyToEnd":2.9},{"zeroToTen":0,"tenToTwenty":0.6,"twentyToThirty":1.2,"thirtyToEnd":2.5},{"zeroToTen":1.6,"tenToTwenty":0.5,"twentyToThirty":1.9,"thirtyToEnd":1.2},{"zeroToTen":0.3,"tenToTwenty":1,"twentyToThirty":1.2,"thirtyToEnd":0.4},{"zeroToTen":0.5,"tenToTwenty":0.6},{"zeroToTen":0.2,"tenToTwenty":1.3,"twentyToThirty":1.9},{"zeroToTen":0,"tenToTwenty":0.3,"twentyToThirty":2},{"zeroToTen":0.4,"tenToTwenty":0.7,"twentyToThirty":2.7},{"zeroToTen":0,"tenToTwenty":1.3},{"zeroToTen":0.4,"tenToTwenty":1.5},{"zeroToTen":0.2,"tenToTwenty":0.7,"twentyToThirty":1.7,"thirtyToEnd":1.2},{"zeroToTen":0.5,"tenToTwenty":0.6,"twentyToThirty":0.4,"thirtyToEnd":3.4666666666667},{"zeroToTen":0,"tenToTwenty":1.7,"twentyToThirty":1.1},{"zeroToTen":0.7,"tenToTwenty":1.4,"twentyToThirty":1.4},{"zeroToTen":0.4,"tenToTwenty":0.6,"twentyToThirty":0.8},{"zeroToTen":0.3,"tenToTwenty":0.3},{"zeroToTen":0.8,"tenToTwenty":1.2,"twentyToThirty":1,"thirtyToEnd":0.2},{"zeroToTen":0.9,"tenToTwenty":1.1,"twentyToThirty":1.9},{"zeroToTen":0.8,"tenToTwenty":0.3,"twentyToThirty":0.6,"thirtyToEnd":0.7},{"zeroToTen":1.3,"tenToTwenty":1.4,"twentyToThirty":2.3,"thirtyToEnd":0.6},{"zeroToTen":1.2,"tenToTwenty":1.4,"twentyToThirty":1.3,"thirtyToEnd":0.6},{"zeroToTen":1,"tenToTwenty":1.7,"twentyToThirty":0.6},{"zeroToTen":1.3,"tenToTwenty":1.9},{"zeroToTen":1.4,"tenToTwenty":2.1},{"zeroToTen":1.3,"tenToTwenty":1.3,"twentyToThirty":1.6,"thirtyToEnd":1.2},{"zeroToTen":1,"tenToTwenty":0.9}],"goldPerMinDeltas":[{"zeroToTen":215.7,"tenToTwenty":355.3,"twentyToThirty":477.3},{"zeroToTen":213.5,"tenToTwenty":324.7,"twentyToThirty":283.2,"thirtyToEnd":462.2},{"zeroToTen":218.7,"tenToTwenty":331.3,"twentyToThirty":400.1,"thirtyToEnd":262.2},{"zeroToTen":262.2,"tenToTwenty":346.9,"twentyToThirty":440.8,"thirtyToEnd":264.7},{"zeroToTen":247.9,"tenToTwenty":312.8,"twentyToThirty":395.1,"thirtyToEnd":337.2},{"zeroToTen":208.2,"tenToTwenty":255.8},{"zeroToTen":251,"tenToTwenty":369.7,"twentyToThirty":411},{"zeroToTen":251.1,"tenToTwenty":292.8,"twentyToThirty":368.4},{"zeroToTen":265.9,"tenToTwenty":199.1,"twentyToThirty":421.2},{"zeroToTen":267,"tenToTwenty":522.5},{"zeroToTen":224.5,"tenToTwenty":384.1},{"zeroToTen":202,"tenToTwenty":305.8,"twentyToThirty":344.1,"thirtyToEnd":268.45},{"zeroToTen":246,"tenToTwenty":316.2,"twentyToThirty":268.4,"thirtyToEnd":316.66666666667},{"zeroToTen":200.6,"tenToTwenty":355,"twentyToThirty":276.8},{"zeroToTen":276.8,"tenToTwenty":414,"twentyToThirty":321.2},{"zeroToTen":201.3,"tenToTwenty":316.9,"twentyToThirty":268.5},{"zeroToTen":184,"tenToTwenty":323.3},{"zeroToTen":139.2,"tenToTwenty":244.4,"twentyToThirty":260.1,"thirtyToEnd":413.2},{"zeroToTen":140.9,"tenToTwenty":240.8,"twentyToThirty":482.4},{"zeroToTen":188.3,"tenToTwenty":193.5,"twentyToThirty":294.2,"thirtyToEnd":315.9},{"zeroToTen":152.3,"tenToTwenty":250.7,"twentyToThirty":307.9,"thirtyToEnd":403},{"zeroToTen":145.3,"tenToTwenty":231.6,"twentyToThirty":271.4,"thirtyToEnd":286.4},{"zeroToTen":172.7,"tenToTwenty":290.5,"twentyToThirty":299},{"zeroToTen":192.8,"tenToTwenty":280.6},{"zeroToTen":150.4,"tenToTwenty":293.9},{"zeroToTen":145.8,"tenToTwenty":262.3,"twentyToThirty":374.7,"thirtyToEnd":232},{"zeroToTen":139.1,"tenToTwenty":224.1}]},"stats":{"wardsPlaced":[13,11,19,13,16,12,12,12,9,9,7,20,19,13,16,14,8,27,23,27,29,32,25,17,18,32,20],"wardsKilled":[2,9,1,7,10,8,0,2,1,1,2,6,10,3,6,2,5,11,5,3,3,5,5,6,4,5,1]}}